{
    "categories": [],
    "coordinates": {
        "latitude": -37.7365608,
        "longitude": 144.8914642
    },
    "id": "bendigo-bank-niddrie",
    "image_url": "",
    "is_claimed": false,
    "is_closed": false,
    "location": {
        "address1": "338A Keilor Rd",
        "address2": null,
        "address3": null,
        "city": "Niddrie",
        "country": "AU",
        "state": "VIC",
        "zip_code": "3042"
    },
    "name": "Bendigo Bank",
    "phone": "+61393798198",
    "photos": [],
    "rating": 5.0,
    "review_count": 1,
    "term": "attractions",
    "url": "https://www.yelp.com/biz/bendigo-bank-niddrie?adjust_creative=92p07_JjKyriZTQxAXRiKQ&utm_campaign=yelp_api_v3&utm_medium=api_v3_business_lookup&utm_source=92p07_JjKyriZTQxAXRiKQ",
    "uuid": "1178"
}