{
    "categories": [
        {
            "alias": "libraries",
            "title": "Libraries"
        }
    ],
    "coordinates": {
        "latitude": 29.794592,
        "longitude": -95.397469
    },
    "hours": [
        {
            "hours_type": "REGULAR",
            "is_open_now": false,
            "open": [
                {
                    "day": 0,
                    "end": "2000",
                    "is_overnight": false,
                    "start": "1200"
                },
                {
                    "day": 1,
                    "end": "1800",
                    "is_overnight": false,
                    "start": "1000"
                },
                {
                    "day": 2,
                    "end": "2000",
                    "is_overnight": false,
                    "start": "1200"
                },
                {
                    "day": 3,
                    "end": "1800",
                    "is_overnight": false,
                    "start": "1000"
                },
                {
                    "day": 4,
                    "end": "1700",
                    "is_overnight": false,
                    "start": "1300"
                },
                {
                    "day": 5,
                    "end": "1700",
                    "is_overnight": false,
                    "start": "1000"
                }
            ]
        }
    ],
    "id": "heights-neighborhood-library-houston-2",
    "image_url": "https://s3-media2.fl.yelpcdn.com/bphoto/deNG4D2d4y0WDquySSKbvA/o.jpg",
    "is_claimed": false,
    "is_closed": false,
    "location": {
        "address1": "1302 Heights Blvd",
        "address2": "",
        "address3": "",
        "city": "Houston",
        "country": "US",
        "state": "TX",
        "zip_code": "77008"
    },
    "name": "Heights Neighborhood Library",
    "phone": "+18323931810",
    "photos": [
        "https://s3-media1.fl.yelpcdn.com/bphoto/deNG4D2d4y0WDquySSKbvA/o.jpg",
        "https://s3-media1.fl.yelpcdn.com/bphoto/tWjo6EhMGRfATumX6i1vIg/o.jpg",
        "https://s3-media2.fl.yelpcdn.com/bphoto/6blsD-7O9poqMvAmf4moRQ/o.jpg"
    ],
    "rating": 3.5,
    "review_count": 16,
    "term": "attractions",
    "url": "https://www.yelp.com/biz/heights-neighborhood-library-houston-2?adjust_creative=92p07_JjKyriZTQxAXRiKQ&utm_campaign=yelp_api_v3&utm_medium=api_v3_business_lookup&utm_source=92p07_JjKyriZTQxAXRiKQ",
    "uuid": "5003"
}