{"response":{"meta":{"hits":928,"time":109,"offset":210},"docs":[{"web_url":"http:\/\/www.nytimes.com\/slideshow\/2017\/02\/03\/style\/riccardo-tiscis-10-noteworthy-red-carpet-moments.html","snippet":"Mr. Tisci has dressed fashion favorites like Beyonc\u00e9, Selena Gomez and Rooney Mara in Givenchy at major events. Here\u2019s a look back....","lead_paragraph":"Mr. Tisci has dressed fashion favorites like Beyonc\u00e9, Selena Gomez and Rooney Mara in Givenchy at major events. Here\u2019s a look back.","abstract":null,"print_page":null,"blog":[],"source":"The New York Times","multimedia":[{"width":190,"url":"images\/2017\/02\/04\/fashion\/03TISCI\/03TISCI-thumbWide.jpg","height":126,"subtype":"wide","legacy":{"wide":"images\/2017\/02\/04\/fashion\/03TISCI\/03TISCI-thumbWide.jpg","wideheight":"126","widewidth":"190"},"type":"image"},{"width":600,"url":"images\/2017\/02\/04\/fashion\/03TISCI\/03TISCI-articleLarge.jpg","height":831,"subtype":"xlarge","legacy":{"xlargewidth":"600","xlarge":"images\/2017\/02\/04\/fashion\/03TISCI\/03TISCI-articleLarge.jpg","xlargeheight":"831"},"type":"image"},{"width":75,"url":"images\/2017\/02\/04\/fashion\/03TISCI\/03TISCI-thumbStandard.jpg","height":75,"subtype":"thumbnail","legacy":{"thumbnailheight":"75","thumbnail":"images\/2017\/02\/04\/fashion\/03TISCI\/03TISCI-thumbStandard.jpg","thumbnailwidth":"75"},"type":"image"}],"headline":{"main":"Riccardo Tisci\u2019s 10 Noteworthy Red Carpet Moments"},"keywords":[],"pub_date":"2017-02-03T18:34:14+0000","document_type":"multimedia","news_desk":"Style","section_name":"Style","subsection_name":null,"byline":[],"type_of_material":"Slideshow","_id":"5894cd2b95d0e0392607e83d","word_count":"22","slideshow_credits":"Dimitrios Kambouris\/Getty Images"},{"web_url":"http:\/\/www.nytimes.com\/aponline\/2017\/02\/03\/us\/politics\/ap-us-trump-russia-fact-check.html","snippet":"Democrats didn't wait to assemble the facts before they accused President Donald Trump of rewarding \"thugs\" in the Russian intelligence service by lifting certain sanctions. The facts don't support them....","lead_paragraph":"Democrats didn't wait to assemble the facts before they accused President Donald Trump of rewarding \"thugs\" in the Russian intelligence service by lifting certain sanctions. The facts don't support them.","abstract":null,"print_page":null,"blog":[],"source":"AP","multimedia":[],"headline":{"main":"AP FACT CHECK: Trump vs. Pelosi on Russia Sanctions","print_headline":"AP FACT CHECK: Trump vs. Pelosi on Russia Sanctions"},"keywords":[],"pub_date":"2017-02-03T18:33:51+0000","document_type":"article","news_desk":null,"section_name":"U.S.","subsection_name":"Politics","byline":{"person":[],"original":"By THE ASSOCIATED PRESS","organization":"THE ASSOCIATED PRESS"},"type_of_material":"News","_id":"5894cd1695d0e0392607e83c","word_count":"424","slideshow_credits":null},{"web_url":"http:\/\/www.nytimes.com\/aponline\/2017\/02\/03\/sports\/basketball\/ap-bkn-cavaliers-love-.html","snippet":"Kevin Love's back spasms have vanished. Those trade rumors won't go away....","lead_paragraph":"Kevin Love's back spasms have vanished. Those trade rumors won't go away.","abstract":null,"print_page":null,"blog":[],"source":"AP","multimedia":[],"headline":{"main":"All-Star Kevin Love Doesn't Expect Cavaliers to Trade Him","print_headline":"All-Star Kevin Love Doesn't Expect Cavaliers to Trade Him"},"keywords":[],"pub_date":"2017-02-03T18:33:47+0000","document_type":"article","news_desk":null,"section_name":"Sports","subsection_name":"Pro Basketball","byline":{"person":[],"original":"By THE ASSOCIATED PRESS","organization":"THE ASSOCIATED PRESS"},"type_of_material":"News","_id":"5894cd1095d0e0392607e83b","word_count":"653","slideshow_credits":null},{"web_url":"http:\/\/www.nytimes.com\/2017\/02\/03\/education\/edlife\/top-20-fields-for-internships-get-your-skills-on.html","snippet":"To get that summer position, here\u2019s what students need to know how to do....","lead_paragraph":"To get that summer position, here\u2019s what students need to know how to do.","abstract":null,"print_page":"2","blog":[],"source":"The New York Times","multimedia":[{"width":190,"url":"images\/2017\/02\/05\/education\/edlife\/05interns-skills-copy\/05interns-skills-copy-thumbWide-v5.jpg","height":126,"subtype":"wide","legacy":{"wide":"images\/2017\/02\/05\/education\/edlife\/05interns-skills-copy\/05interns-skills-copy-thumbWide-v5.jpg","wideheight":"126","widewidth":"190"},"type":"image"},{"width":600,"url":"images\/2017\/02\/05\/education\/edlife\/05interns-skills-copy\/05interns-skills-copy-articleLarge-v6.jpg","height":111,"subtype":"xlarge","legacy":{"xlargewidth":"600","xlarge":"images\/2017\/02\/05\/education\/edlife\/05interns-skills-copy\/05interns-skills-copy-articleLarge-v6.jpg","xlargeheight":"111"},"type":"image"},{"width":75,"url":"images\/2017\/02\/05\/education\/edlife\/05interns-skills-copy\/05interns-skills-copy-thumbStandard-v5.jpg","height":75,"subtype":"thumbnail","legacy":{"thumbnailheight":"75","thumbnail":"images\/2017\/02\/05\/education\/edlife\/05interns-skills-copy\/05interns-skills-copy-thumbStandard-v5.jpg","thumbnailwidth":"75"},"type":"image"}],"headline":{"main":"Top 20 Fields for Internships: Get Your Skills On","content_kicker":"The List","kicker":"The List","print_headline":"Get Your Skills On"},"keywords":[{"rank":"1","is_major":"N","name":"subject","value":"Internships"},{"rank":"2","is_major":"N","name":"subject","value":"Labor and Jobs"},{"rank":"3","is_major":"N","name":"subject","value":"Colleges and Universities"}],"pub_date":"2017-02-03T18:31:51+0000","document_type":"article","news_desk":"EdLife","section_name":"Education","subsection_name":"Education Life","byline":[],"type_of_material":"News","_id":"5894cc9c95d0e0392607e83a","word_count":"426","slideshow_credits":null},{"web_url":"http:\/\/www.nytimes.com\/2017\/02\/03\/dining\/ricotta-gnocchi-dumpling-recipe.html","snippet":"Beginner\u2019s attempts at potato gnocchi usually produce tough, chewy specimens, but most home cooks can find success making a ricotta version....","lead_paragraph":"Beginner\u2019s attempts at potato gnocchi usually produce tough, chewy specimens, but most home cooks can find success making a ricotta version.","abstract":null,"print_page":"2","blog":[],"source":"The New York Times","multimedia":[{"width":190,"url":"images\/2017\/02\/08\/dining\/08KITCH1\/08KITCH1-thumbWide-v2.jpg","height":126,"subtype":"wide","legacy":{"wide":"images\/2017\/02\/08\/dining\/08KITCH1\/08KITCH1-thumbWide-v2.jpg","wideheight":"126","widewidth":"190"},"type":"image"},{"width":600,"url":"images\/2017\/02\/08\/dining\/08KITCH1\/08KITCH1-articleLarge.jpg","height":401,"subtype":"xlarge","legacy":{"xlargewidth":"600","xlarge":"images\/2017\/02\/08\/dining\/08KITCH1\/08KITCH1-articleLarge.jpg","xlargeheight":"401"},"type":"image"},{"width":75,"url":"images\/2017\/02\/08\/dining\/08KITCH1\/08KITCH1-thumbStandard.jpg","height":75,"subtype":"thumbnail","legacy":{"thumbnailheight":"75","thumbnail":"images\/2017\/02\/08\/dining\/08KITCH1\/08KITCH1-thumbStandard.jpg","thumbnailwidth":"75"},"type":"image"}],"headline":{"main":"A Savory, Tender Gnocchi Poised for Success","content_kicker":"City Kitchen","kicker":"City Kitchen","print_headline":"For Gnocchi Success, Start With Ricotta"},"keywords":[{"rank":"1","is_major":"N","name":"subject","value":"Cooking and Cookbooks"},{"rank":"2","is_major":"N","name":"subject","value":"Cheese"},{"rank":"3","is_major":"N","name":"glocations","value":"Italy"}],"pub_date":"2017-02-03T18:31:16+0000","document_type":"article","news_desk":"Dining","section_name":"Food","subsection_name":null,"byline":{"contributor":"","person":[{"organization":"","role":"reported","firstname":"David","rank":1,"lastname":"TANIS"}],"original":"By DAVID TANIS"},"type_of_material":"News","_id":"5894cc7c95d0e0392607e839","word_count":"604","slideshow_credits":null},{"web_url":"http:\/\/www.nytimes.com\/aponline\/2017\/02\/03\/us\/ap-us-shooting-ohio-school.html","snippet":"An Ohio judge has ordered a competency evaluation for a 17-year-old student charged in a school shooting....","lead_paragraph":"An Ohio judge has ordered a competency evaluation for a 17-year-old student charged in a school shooting.","abstract":null,"print_page":null,"blog":[],"source":"AP","multimedia":[],"headline":{"main":"Competency Evaluation Ordered for School Shooting Suspect","print_headline":"Competency Evaluation Ordered for School Shooting Suspect"},"keywords":[],"pub_date":"2017-02-03T18:30:42+0000","document_type":"article","news_desk":null,"section_name":"U.S.","subsection_name":null,"byline":{"person":[],"original":"By THE ASSOCIATED PRESS","organization":"THE ASSOCIATED PRESS"},"type_of_material":"News","_id":"5894cc5995d0e0392607e838","word_count":"121","slideshow_credits":null},{"web_url":"http:\/\/www.nytimes.com\/reuters\/2017\/02\/03\/world\/europe\/03reuters-eurozone-greece-germany.html","snippet":"Germany's government said on Friday it remained united on the need to stabilise the Greek economy despite indications of divergent views between Chancellor Angela Merkel's conservatives and their Social Democratic coalition partners....","lead_paragraph":"Germany's government said on Friday it remained united on the need to stabilise the Greek economy despite indications of divergent views between Chancellor Angela Merkel's conservatives and their Social Democratic coalition partners.","abstract":null,"print_page":null,"blog":[],"source":"Reuters","multimedia":[],"headline":{"main":"German Government Says United on Greece, Plays Down Talk of Splits","print_headline":"German Government Says United on Greece, Plays Down Talk of Splits"},"keywords":[],"pub_date":"2017-02-03T18:30:27+0000","document_type":"article","news_desk":null,"section_name":"World","subsection_name":"Europe","byline":{"person":[],"original":"By REUTERS","organization":"REUTERS"},"type_of_material":"News","_id":"5894cc4b95d0e0392607e837","word_count":"470","slideshow_credits":null},{"web_url":"http:\/\/www.nytimes.com\/aponline\/2017\/02\/03\/sports\/baseball\/ap-bba-royals-herrera.html","snippet":"The Royals felt comfortable trading star closer Wade Davis in part because they had Kelvin Herrera, a two-time All-Star in his own right, ready to assume the job this season....","lead_paragraph":"The Royals felt comfortable trading star closer Wade Davis in part because they had Kelvin Herrera, a two-time All-Star in his own right, ready to assume the job this season.","abstract":null,"print_page":null,"blog":[],"source":"AP","multimedia":[],"headline":{"main":"Royals, Herrera Agree to $5,325,000 Deal, Avoid Arbitration","print_headline":"Royals, Herrera Agree to $5,325,000 Deal, Avoid Arbitration"},"keywords":[],"pub_date":"2017-02-03T18:27:42+0000","document_type":"article","news_desk":null,"section_name":"Sports","subsection_name":"Baseball","byline":{"person":[],"original":"By THE ASSOCIATED PRESS","organization":"THE ASSOCIATED PRESS"},"type_of_material":"News","_id":"5894cba895d0e0392607e836","word_count":"310","slideshow_credits":null},{"web_url":"http:\/\/www.nytimes.com\/2017\/02\/03\/insider\/three-pens-a-notebook-and-questions-inside-a-late-night-assignment.html","snippet":"The reporter Nicholas Kulish describes how he roused himself from half-sleep, ordered a Lyft and helped report on refugees detained at J.F.K. airport....","lead_paragraph":"The reporter Nicholas Kulish describes how he roused himself from half-sleep, ordered a Lyft and helped report on refugees detained at J.F.K. airport.","abstract":null,"print_page":null,"blog":[],"source":"The New York Times","multimedia":[{"width":190,"url":"images\/2017\/01\/28\/us\/29doorcloses-slide-UB19\/29doorcloses-slide-UB19-thumbWide-v2.jpg","height":126,"subtype":"wide","legacy":{"wide":"images\/2017\/01\/28\/us\/29doorcloses-slide-UB19\/29doorcloses-slide-UB19-thumbWide-v2.jpg","wideheight":"126","widewidth":"190"},"type":"image"},{"width":600,"url":"images\/2017\/01\/28\/us\/29doorcloses-slide-UB19\/29doorcloses-slide-UB19-articleLarge-v2.jpg","height":400,"subtype":"xlarge","legacy":{"xlargewidth":"600","xlarge":"images\/2017\/01\/28\/us\/29doorcloses-slide-UB19\/29doorcloses-slide-UB19-articleLarge-v2.jpg","xlargeheight":"400"},"type":"image"},{"width":75,"url":"images\/2017\/01\/28\/us\/29doorcloses-slide-UB19\/29doorcloses-slide-UB19-thumbStandard-v3.jpg","height":75,"subtype":"thumbnail","legacy":{"thumbnailheight":"75","thumbnail":"images\/2017\/01\/28\/us\/29doorcloses-slide-UB19\/29doorcloses-slide-UB19-thumbStandard-v3.jpg","thumbnailwidth":"75"},"type":"image"}],"headline":{"main":"Three Pens, a Notebook and Questions: Inside a Late-Night Assignment"},"keywords":[{"rank":"1","is_major":"N","name":"subject","value":"Executive Orders and Memorandums"},{"rank":"11","is_major":"N","name":"persons","value":"Darweesh, Hameed Khalid"},{"rank":"12","is_major":"N","name":"persons","value":"Nadler, Jerrold"},{"rank":"13","is_major":"N","name":"glocations","value":"Houston (Tex)"},{"rank":"2","is_major":"N","name":"subject","value":"Airports"},{"rank":"3","is_major":"N","name":"subject","value":"Refugees and Displaced Persons"},{"rank":"4","is_major":"N","name":"subject","value":"Deportation"},{"rank":"5","is_major":"N","name":"organizations","value":"American Civil Liberties Union"},{"rank":"6","is_major":"N","name":"organizations","value":"Customs and Border Protection (US)"},{"rank":"7","is_major":"N","name":"organizations","value":"Dunkin Donuts"},{"rank":"8","is_major":"N","name":"organizations","value":"Kennedy International Airport (Queens, NY)"},{"rank":"9","is_major":"N","name":"organizations","value":"National Immigration Law Center"},{"rank":"10","is_major":"N","name":"organizations","value":"Yale University"}],"pub_date":"2017-02-03T18:25:40+0000","document_type":"article","news_desk":"Insider","section_name":"Times Insider","subsection_name":null,"byline":{"person":[{"organization":"","role":"reported","firstname":"Nicholas","rank":1,"lastname":"KULISH"}],"original":"By NICHOLAS KULISH"},"type_of_material":"News","_id":"5894cb2d95d0e0392607e834","word_count":"1371","slideshow_credits":null},{"web_url":"http:\/\/www.nytimes.com\/2017\/02\/03\/health\/sounds-people-hate.html","snippet":"To those for whom ordinary sounds cause extraordinary rage, a new study may help lead to relief....","lead_paragraph":"To those for whom ordinary sounds cause extraordinary rage, a new study may help lead to relief.","abstract":null,"print_page":null,"blog":[],"source":"The New York Times","multimedia":[{"width":190,"url":"images\/2017\/02\/04\/us\/04xp-misophonia\/04xp-misophonia-thumbWide.jpg","height":126,"subtype":"wide","legacy":{"wide":"images\/2017\/02\/04\/us\/04xp-misophonia\/04xp-misophonia-thumbWide.jpg","wideheight":"126","widewidth":"190"},"type":"image"},{"width":600,"url":"images\/2017\/02\/04\/us\/04xp-misophonia\/04xp-misophonia-articleLarge.jpg","height":400,"subtype":"xlarge","legacy":{"xlargewidth":"600","xlarge":"images\/2017\/02\/04\/us\/04xp-misophonia\/04xp-misophonia-articleLarge.jpg","xlargeheight":"400"},"type":"image"},{"width":75,"url":"images\/2017\/02\/04\/us\/04xp-misophonia\/04xp-misophonia-thumbStandard.jpg","height":75,"subtype":"thumbnail","legacy":{"thumbnailheight":"75","thumbnail":"images\/2017\/02\/04\/us\/04xp-misophonia\/04xp-misophonia-thumbStandard.jpg","thumbnailwidth":"75"},"type":"image"}],"headline":{"main":"Misophonia Sufferers: Scientists May Have Found the Root of Your Pain"},"keywords":[{"rank":"1","is_major":"N","name":"subject","value":"Noise"},{"rank":"2","is_major":"N","name":"subject","value":"Mental Health and Disorders"},{"rank":"3","is_major":"N","name":"subject","value":"Anxiety and Stress"},{"rank":"4","is_major":"N","name":"organizations","value":"Newcastle University"}],"pub_date":"2017-02-03T18:25:13+0000","document_type":"article","news_desk":"Science","section_name":"Health","subsection_name":null,"byline":{"person":[{"organization":"","role":"reported","firstname":"Kimiko","rank":1,"lastname":"de FREYTAS-TAMURA"}],"original":"By KIMIKO de FREYTAS-TAMURA"},"type_of_material":"News","_id":"5894cb0e95d0e0392607e833","word_count":"559","slideshow_credits":null}]},"status":"OK","copyright":"Copyright (c) 2013 The New York Times Company.  All Rights Reserved."}